bidsmreye/__init__.py
bidsmreye/_cli.py
bidsmreye/_parsers.py
bidsmreye/_version.py
bidsmreye/bids_utils.py
bidsmreye/bidsmreye.py
bidsmreye/configuration.py
bidsmreye/defaults.py
bidsmreye/download.py
bidsmreye/generalize.py
bidsmreye/logger.py
bidsmreye/methods.py
bidsmreye/prepare_data.py
bidsmreye/quality_control.py
bidsmreye/report.py
bidsmreye/utils.py
bidsmreye/visualize.py
bidsmreye/config/config_bidsname.json
bidsmreye/config/config_pybids.json
bidsmreye/config/default_filter_file.json
bidsmreye/models/README.md
bidsmreye/models/registry.txt
bidsmreye/templates/CCO
bidsmreye/templates/CITATION.bib
bidsmreye/templates/CITATION.jinja
bidsmreye/templates/report/base.html
bidsmreye/templates/report/footer.html
bidsmreye/templates/report/header.html
bidsmreye-0.5.0.dist-info/METADATA
bidsmreye-0.5.0.dist-info/WHEEL
bidsmreye-0.5.0.dist-info/entry_points.txt
bidsmreye-0.5.0.dist-info/licenses/LICENSE
bidsmreye-0.5.0.dist-info/RECORD
