Metadata-Version: 2.3
Name: bidsmreye
Version: 0.5.0
Summary: bids app using deepMReye to decode eye motion for fMRI time series data
Project-URL: Bug Tracker, https://github.com/cpp-lln-lab/bidsMReye/issues
Project-URL: Homepage, https://github.com/cpp-lln-lab/bidsMReye
Author-email: Remi Gau <remi.gau@gmail.com>
License: GNU GENERAL PUBLIC LICENSE
License-File: LICENSE
Keywords: BIDS,Eyetracking,MRI,Machine learning,automated pipeline,brain imaging data structure,neuroimaging
Classifier: Development Status :: 3 - Alpha
Classifier: Intended Audience :: Science/Research
Classifier: License :: OSI Approved :: GNU Lesser General Public License v3 (LGPLv3)
Classifier: Operating System :: Unix
Classifier: Programming Language :: Python
Classifier: Programming Language :: Python :: 3.9
Classifier: Programming Language :: Python :: 3.10
Classifier: Programming Language :: Python :: 3.11
Classifier: Topic :: Scientific/Engineering :: Artificial Intelligence
Classifier: Topic :: Scientific/Engineering :: Image Processing
Requires-Python: >=3.9.0
Requires-Dist: antspyx<0.5
Requires-Dist: attrs
Requires-Dist: deepmreye>=0.2.1
Requires-Dist: jinja2
Requires-Dist: kaleido
Requires-Dist: keras<3.0.0
Requires-Dist: pooch>=1.6.0
Requires-Dist: pybids
Requires-Dist: rich-argparse
Requires-Dist: tomli; python_version < '3.11'
Requires-Dist: tqdm
Provides-Extra: dev
Requires-Dist: faqtory; extra == 'dev'
Requires-Dist: myst-parser; extra == 'dev'
Requires-Dist: pre-commit; extra == 'dev'
Requires-Dist: pytest; extra == 'dev'
Requires-Dist: pytest-cov; extra == 'dev'
Requires-Dist: rstcheck; extra == 'dev'
Requires-Dist: sourcery; extra == 'dev'
Requires-Dist: sphinx; extra == 'dev'
Requires-Dist: sphinx-argparse; extra == 'dev'
Requires-Dist: sphinx-copybutton; extra == 'dev'
Requires-Dist: sphinx-rtd-theme; extra == 'dev'
Requires-Dist: sphinxcontrib-bibtex; extra == 'dev'
Provides-Extra: doc
Requires-Dist: faqtory; extra == 'doc'
Requires-Dist: myst-parser; extra == 'doc'
Requires-Dist: rstcheck; extra == 'doc'
Requires-Dist: sphinx; extra == 'doc'
Requires-Dist: sphinx-argparse; extra == 'doc'
Requires-Dist: sphinx-copybutton; extra == 'doc'
Requires-Dist: sphinx-rtd-theme; extra == 'doc'
Requires-Dist: sphinxcontrib-bibtex; extra == 'doc'
Provides-Extra: docs
Requires-Dist: faqtory; extra == 'docs'
Requires-Dist: myst-parser; extra == 'docs'
Requires-Dist: rstcheck; extra == 'docs'
Requires-Dist: sphinx; extra == 'docs'
Requires-Dist: sphinx-argparse; extra == 'docs'
Requires-Dist: sphinx-copybutton; extra == 'docs'
Requires-Dist: sphinx-rtd-theme; extra == 'docs'
Requires-Dist: sphinxcontrib-bibtex; extra == 'docs'
Provides-Extra: style
Requires-Dist: pre-commit; extra == 'style'
Requires-Dist: sourcery; extra == 'style'
Provides-Extra: test
Requires-Dist: pytest; extra == 'test'
Requires-Dist: pytest-cov; extra == 'test'
Provides-Extra: tests
Requires-Dist: pytest; extra == 'tests'
Requires-Dist: pytest-cov; extra == 'tests'
